synap_sdk/__init__.py
synap_sdk/client.py
synap_sdk/config.py
synap_sdk/exceptions.py
synap_sdk/types.py
synap_sdk/modules/__init__.py
synap_sdk/modules/kv_store.py
synap_sdk/modules/pubsub.py
synap_sdk/modules/queue.py
synap_sdk/modules/stream.py
synap_sdk-0.1.0.dist-info/METADATA
synap_sdk-0.1.0.dist-info/WHEEL
synap_sdk-0.1.0.dist-info/licenses/LICENSE
synap_sdk-0.1.0.dist-info/RECORD
