Metadata-Version: 2.4
Name: synap_sdk
Version: 0.1.0
Summary: Official Python SDK for Synap - High-Performance In-Memory Key-Value Store & Message Broker
Project-URL: Homepage, https://github.com/hivellm/hivellm
Project-URL: Documentation, https://github.com/hivellm/hivellm/blob/main/synap/README.md
Project-URL: Repository, https://github.com/hivellm/hivellm
Project-URL: Issues, https://github.com/hivellm/hivellm/issues
Author-email: HiveLLM <contact@hivellm.com>
License-Expression: MIT
License-File: LICENSE
Keywords: event-stream,kafka,kv-store,message-queue,pubsub,rabbitmq,redis,synap
Classifier: Development Status :: 4 - Beta
Classifier: Intended Audience :: Developers
Classifier: License :: OSI Approved :: MIT License
Classifier: Operating System :: OS Independent
Classifier: Programming Language :: Python :: 3
Classifier: Programming Language :: Python :: 3.11
Classifier: Programming Language :: Python :: 3.12
Classifier: Topic :: Software Development :: Libraries :: Python Modules
Classifier: Typing :: Typed
Requires-Python: >=3.11
Requires-Dist: httpx>=0.27.0
Provides-Extra: dev
Requires-Dist: mypy>=1.9.0; extra == 'dev'
Requires-Dist: pytest-asyncio>=0.23.0; extra == 'dev'
Requires-Dist: pytest-cov>=4.1.0; extra == 'dev'
Requires-Dist: pytest>=8.0.0; extra == 'dev'
Requires-Dist: ruff>=0.3.0; extra == 'dev'
